{
    "key": "group_6673fcaca4c3e",
    "title": "Product details",
    "fields": [
        {
            "key": "field_6673fcaca6266",
            "label": "Product details",
            "name": "",
            "aria-label": "",
            "type": "accordion",
            "instructions": "",
            "required": 0,
            "conditional_logic": 0,
            "wrapper": {
                "width": "",
                "class": "",
                "id": ""
            },
            "open": 1,
            "multi_expand": 0,
            "endpoint": 0
        },
        {
            "key": "field_6673fd2f82c8d",
            "label": "Tabs",
            "name": "tabs",
            "aria-label": "",
            "type": "repeater",
            "instructions": "",
            "required": 0,
            "conditional_logic": 0,
            "wrapper": {
                "width": "",
                "class": "",
                "id": ""
            },
            "layout": "block",
            "pagination": 0,
            "min": 0,
            "max": 0,
            "collapsed": "field_6673fd4c82c8e",
            "button_label": "Nieuwe tab",
            "rows_per_page": 20,
            "sub_fields": [
                {
                    "key": "field_6673fd4c82c8e",
                    "label": "Title",
                    "name": "title",
                    "aria-label": "",
                    "type": "text",
                    "instructions": "",
                    "required": 0,
                    "conditional_logic": 0,
                    "wrapper": {
                        "width": "",
                        "class": "",
                        "id": ""
                    },
                    "default_value": "",
                    "maxlength": "",
                    "placeholder": "",
                    "prepend": "",
                    "append": "",
                    "parent_repeater": "field_6673fd2f82c8d"
                },
                {
                    "key": "field_6673fd5982c8f",
                    "label": "Text",
                    "name": "text",
                    "aria-label": "",
                    "type": "wysiwyg",
                    "instructions": "",
                    "required": 0,
                    "conditional_logic": 0,
                    "wrapper": {
                        "width": "",
                        "class": "",
                        "id": ""
                    },
                    "default_value": "",
                    "tabs": "all",
                    "toolbar": "full",
                    "media_upload": 1,
                    "delay": 0,
                    "parent_repeater": "field_6673fd2f82c8d"
                }
            ]
        }
    ],
    "location": [
        [
            {
                "param": "post_type",
                "operator": "==",
                "value": "product"
            }
        ]
    ],
    "menu_order": 5,
    "position": "normal",
    "style": "seamless",
    "label_placement": "top",
    "instruction_placement": "label",
    "hide_on_screen": "",
    "active": true,
    "description": "",
    "show_in_rest": 0,
    "modified": 1718877624
}
